{
	"casino_jazz":"casino-jazz.mp3",
	"chips_bet":"chips_bet.wav",
	"bravo":"crowd_shouts_yeah_exterior_rock_concert_ocm-0055-342.wav",
	"dealing_cards":"dealing_cards.wav",
	"banker_wins":"banker-wins.mp3",
	"player_wins":"player-wins.mp3",
	"tie_hand": "tie-hand.mp3",
	"banker_0": "banker-0.mp3",
	"banker_1": "banker-1.mp3",
	"banker_2": "banker-2.mp3",
	"banker_3": "banker-3.mp3",
	"banker_4": "banker-4.mp3",
	"banker_5": "banker-5.mp3",
	"banker_6": "banker-6.mp3",
	"banker_7": "banker-7.mp3",
	"banker_8": "banker-8.mp3",
	"banker_9": "banker-9.mp3",
	"banker_dragon_1":"banker-1-to-1-dragon.mp3",
	"banker_dragon_2":"banker-2-to-1-dragon.mp3",
	"banker_dragon_4":"banker-4-to-1-dragon.mp3",
	"banker_dragon_6":"banker-6-to-1-dragon.mp3",
	"banker_dragon_10":"banker-10-to-1-dragon.mp3",
	"banker_dragon_30":"banker-30-to-1-dragon.mp3",
	"banker_natural_8":"banker-natural-8.mp3",
	"banker_natural_9":"banker-natural-9.mp3",
	"player_0":"player-0.mp3",
	"player_1":"player-1.mp3",
	"player_2":"player-2.mp3",
	"player_3":"player-3.mp3",
	"player_4":"player-4.mp3",
	"player_5":"player-5.mp3",
	"player_6":"player-6.mp3",
	"player_7":"player-7.mp3",
	"player_8":"player-8.mp3",
	"player_9":"player-9.mp3",
	"player_dragon_1":"player-1-to-1-dragon.mp3",
	"player_dragon_2":"player-2-to-1-dragon.mp3",
	"player_dragon_4":"player-4-to-1-dragon.mp3",
	"player_dragon_6":"player-6-to-1-dragon.mp3",
	"player_dragon_10":"player-10-to-1-dragon.mp3",
	"player_dragon_30":"player-30-to-1-dragon.mp3",
	"player_natural_8":"player-natural-8.mp3",
	"player_natural_9":"player-natural-9.mp3"
}